LICENSE
README.rst
setup.cfg
setup.py
lce/__init__.py
lce/_catboost.py
lce/_lce.py
lce/_lcetree.py
lce/_lightgbm.py
lce/_version.py
lce/_xgboost.py
lce/tests/__init__.py
lce/tests/test_lce.py
lcensemble.egg-info/PKG-INFO
lcensemble.egg-info/SOURCES.txt
lcensemble.egg-info/dependency_links.txt
lcensemble.egg-info/not-zip-safe
lcensemble.egg-info/requires.txt
lcensemble.egg-info/top_level.txt