Metadata-Version: 2.1
Name: lcensemble
Version: 0.3.4
Summary: Local Cascade Ensemble package
Home-page: https://lce.readthedocs.io/en/latest/
Download-URL: https://github.com/LocalCascadeEnsemble/LCE
Maintainer: Kevin Fauvel
Maintainer-email: kfauvel.lce@gmail.com
License: Apache-2.0
Project-URL: Documentation, https://lce.readthedocs.io/en/latest/
Classifier: License :: OSI Approved :: Apache Software License
Classifier: Programming Language :: Python :: 3
Classifier: Programming Language :: Python :: 3.8
Classifier: Programming Language :: Python :: 3.9
Classifier: Programming Language :: Python :: 3.10
Classifier: Operating System :: OS Independent
Requires-Python: >=3.8
Provides-Extra: tests
Provides-Extra: docs
License-File: LICENSE
